quollio_core/__init__.py
quollio_core/bigquery.py
quollio_core/bricks.py
quollio_core/redshift.py
quollio_core/snowflake.py
quollio_core/teradata.py
quollio_core/dbt_projects/databricks/.gitignore
quollio_core/dbt_projects/databricks/README.md
quollio_core/dbt_projects/databricks/dbt_project.yml
quollio_core/dbt_projects/databricks/packages_hub.yml
quollio_core/dbt_projects/databricks/packages_local.yml
quollio_core/dbt_projects/databricks/analyses/.gitkeep
quollio_core/dbt_projects/databricks/macros/.gitkeep
quollio_core/dbt_projects/databricks/models/quollio_lineage_column_level.sql
quollio_core/dbt_projects/databricks/models/quollio_lineage_column_level.yml
quollio_core/dbt_projects/databricks/models/quollio_lineage_table_level.sql
quollio_core/dbt_projects/databricks/models/quollio_lineage_table_level.yml
quollio_core/dbt_projects/databricks/models/sources.yml
quollio_core/dbt_projects/databricks/profiles/profiles_template.yml
quollio_core/dbt_projects/databricks/seeds/.gitkeep
quollio_core/dbt_projects/databricks/snapshots/.gitkeep
quollio_core/dbt_projects/redshift/README.md
quollio_core/dbt_projects/redshift/dbt_project.yml
quollio_core/dbt_projects/redshift/packages_hub.yml
quollio_core/dbt_projects/redshift/packages_local.yml
quollio_core/dbt_projects/redshift/analyses/.gitkeep
quollio_core/dbt_projects/redshift/macros/.gitkeep
quollio_core/dbt_projects/redshift/macros/materialization/divided_view.sql
quollio_core/dbt_projects/redshift/models/quollio_lineage_table_level.sql
quollio_core/dbt_projects/redshift/models/quollio_lineage_table_level.yml
quollio_core/dbt_projects/redshift/models/quollio_lineage_view_level.sql
quollio_core/dbt_projects/redshift/models/quollio_lineage_view_level.yml
quollio_core/dbt_projects/redshift/models/quollio_sqllineage_sources.sql
quollio_core/dbt_projects/redshift/models/quollio_sqllineage_sources.yml
quollio_core/dbt_projects/redshift/models/quollio_stats_columns.sql
quollio_core-0.8.3.dist-info/licenses/LICENSE
quollio_core-0.8.3.dist-info/WHEEL
quollio_core-0.8.3.dist-info/METADATA
quollio_core-0.8.3.dist-info/RECORD
