Metadata-Version: 2.4
Name: quollio-core
Version: 0.8.3
Summary: Quollio Core
Author-email: quollio-dev <qt.dev@quollio.com>
Maintainer-email: RyoAriyama <ryo.arym@gmail.com>, tharuta <35373297+TakumiHaruta@users.noreply.github.com>
Requires-Python: >=3.9
Classifier: Programming Language :: Python
Classifier: Programming Language :: Python :: 3
Classifier: Programming Language :: Python :: 3.9
Classifier: Programming Language :: Python :: 3.10
Classifier: Programming Language :: Python :: 3.11
Classifier: License :: OSI Approved :: GNU Affero General Public License v3
Classifier: Operating System :: OS Independent
Classifier: Development Status :: 3 - Alpha
Classifier: Intended Audience :: Developers
Classifier: Topic :: Software Development :: Libraries :: Python Modules
License-File: LICENSE
Requires-Dist: blake3==0.3.3
Requires-Dist: dbt-core==1.8.8
Requires-Dist: dbt-snowflake==1.8.4
Requires-Dist: dbt-redshift==1.8.1
Requires-Dist: dbt-databricks==1.8.7
Requires-Dist: db-dtypes==1.2.0
Requires-Dist: jinja2==3.1.3
Requires-Dist: PyYAML==6.0.1
Requires-Dist: requests==2.31.0
Requires-Dist: pyjwt==2.8.0
Requires-Dist: redshift-connector==2.0.915
Requires-Dist: snowflake-connector-python==3.15.0
Requires-Dist: databricks-sdk==0.17.0
Requires-Dist: databricks-sql-connector==3.1.2
Requires-Dist: sqlglot==20.8.0
Requires-Dist: google-cloud==0.34.0
Requires-Dist: google-cloud-bigquery==3.22.0
Requires-Dist: google-cloud-datacatalog==3.19.0
Requires-Dist: google-cloud-datacatalog-lineage==0.3.6
Requires-Dist: google-api-python-client==2.131.0
Requires-Dist: teradatasql==20.0.0.15
Requires-Dist: dataclasses_avroschema==0.63.9
Requires-Dist: fastavro==1.9.7
Requires-Dist: black>=22.3.0 ; extra == "test"
Requires-Dist: coverage>=7.3.2 ; extra == "test"
Requires-Dist: isort>=5.10.1 ; extra == "test"
Requires-Dist: pyproject-flake8>=0.0.1-alpha.2 ; extra == "test"
Requires-Dist: pytest>=5.2 ; extra == "test"
Requires-Dist: responses>=0.25.3 ; extra == "test"
Requires-Dist: dbt-osmosis==0.12.5 ; extra == "test"
Project-URL: Home, https://quollio.com
Project-URL: Source, https://github.com/QuollioLabs/quollio-core
Provides-Extra: test
